astock_loaders/__init__.py
astock_loaders/base_loader.py
astock_loaders/index_trend_loader.py
astock_loaders/stock_base_loader.py
astock_loaders/stock_dataset.py
astock_loaders/stock_kline_loader.py
astock_loaders/stock_market_loader.py
astock_loaders/stock_trend_loader.py
astock_loaders/utils.py
astock_loaders-0.1.8.dist-info/METADATA
astock_loaders-0.1.8.dist-info/WHEEL
astock_loaders-0.1.8.dist-info/RECORD
