Metadata-Version: 2.1
Name: astock-loaders
Version: 0.1.8
Summary: A股市场分析提供强大的训练和测试数据集，支持大型模型开发。它生成适用于金融数据处理的Keras数据加载器，简化数据准备过程，使分析师和数据科学家专注于模型开发。功能包括数据标准化、增强和批处理，是在A股市场领域利用深度学习技术的必备工具。
Author: sunjuzhong
Author-email: 129019668+sunjuzhong@users.noreply.github.com
Requires-Python: >=3.10,<4.0
Classifier: Programming Language :: Python :: 3
Classifier: Programming Language :: Python :: 3.10
Classifier: Programming Language :: Python :: 3.11
Classifier: Programming Language :: Python :: 3.12
Classifier: Programming Language :: Python :: 3.13
Requires-Dist: china-stock-data (>=0.1.6,<0.2.0)
Requires-Dist: matplotlib (>=3.10.0,<4.0.0)
Requires-Dist: mplfinance (>=0.12.10b0,<0.13.0)
Requires-Dist: scikit-learn (>=1.6.0,<2.0.0)
Requires-Dist: torch (>=2.5.1,<3.0.0)
